tundra/__init__.py
tundra/entities.py
tundra/error.py
tundra/logger.py
tundra/snowflake_connector.py
tundra/snowflake_grants.py
tundra/snowflake_permission.py
tundra/snowflake_role_grant_checker.py
tundra/snowflake_spec_loader.py
tundra/spec_file_loader.py
tundra/types.py
tundra/cli/__init__.py
tundra/cli/__main__.py
tundra/cli/cli.py
tundra/cli/permissions.py
tundra/spec_schemas/__init__.py
tundra/spec_schemas/snowflake.py
tundra_cli-0.0.5.dist-info/licenses/LICENSE
tundra_cli-0.0.5.dist-info/METADATA
tundra_cli-0.0.5.dist-info/WHEEL
tundra_cli-0.0.5.dist-info/entry_points.txt
tundra_cli-0.0.5.dist-info/top_level.txt
tundra_cli-0.0.5.dist-info/RECORD
