Metadata-Version: 2.4
Name: tundra-cli
Version: 0.0.5
Summary: Snowflake permissions management tool with Apache Iceberg table support
Author-email: Henry Upton <henryupton@gmail.com>
License: MIT
Project-URL: Homepage, https://github.com/henryupton/tundra
Project-URL: Repository, https://github.com/henryupton/tundra
Project-URL: Issues, https://github.com/henryupton/tundra/issues
Keywords: snowflake,permissions,iceberg,data,warehouse,tundra,access-control
Classifier: Programming Language :: Python :: 3
Classifier: License :: OSI Approved :: MIT License
Classifier: Operating System :: OS Independent
Requires-Python: >=3.8
License-File: LICENSE
Requires-Dist: cerberus
Requires-Dist: colorama
Requires-Dist: coloredlogs
Requires-Dist: click
Requires-Dist: click-default-group
Requires-Dist: pyyaml
Requires-Dist: snowflake-connector-python[secure-local-storage]
Requires-Dist: snowflake-sqlalchemy
Requires-Dist: sqlalchemy
Provides-Extra: dev
Requires-Dist: black; extra == "dev"
Requires-Dist: bumpversion; extra == "dev"
Requires-Dist: changelog-cli; extra == "dev"
Requires-Dist: coverage; extra == "dev"
Requires-Dist: flake8; extra == "dev"
Requires-Dist: isort; extra == "dev"
Requires-Dist: mypy; extra == "dev"
Requires-Dist: pre-commit; extra == "dev"
Requires-Dist: pytest; extra == "dev"
Requires-Dist: pytest-cov; extra == "dev"
Requires-Dist: pytest-mock; extra == "dev"
Requires-Dist: types-PyYAML; extra == "dev"
Dynamic: license-file
